odoo/addons/purchase_unreconciled/README.rst
odoo/addons/purchase_unreconciled/__init__.py
odoo/addons/purchase_unreconciled/__manifest__.py
odoo/addons/purchase_unreconciled/i18n/it.po
odoo/addons/purchase_unreconciled/i18n/pt_BR.po
odoo/addons/purchase_unreconciled/i18n/purchase_unreconciled.pot
odoo/addons/purchase_unreconciled/models/__init__.py
odoo/addons/purchase_unreconciled/models/account_move_line.py
odoo/addons/purchase_unreconciled/models/company.py
odoo/addons/purchase_unreconciled/models/purchase_order.py
odoo/addons/purchase_unreconciled/models/res_config_settings.py
odoo/addons/purchase_unreconciled/readme/CONTRIBUTORS.md
odoo/addons/purchase_unreconciled/readme/DESCRIPTION.md
odoo/addons/purchase_unreconciled/readme/USAGE.md
odoo/addons/purchase_unreconciled/security/ir.model.access.csv
odoo/addons/purchase_unreconciled/static/description/icon.png
odoo/addons/purchase_unreconciled/static/description/index.html
odoo/addons/purchase_unreconciled/tests/__init__.py
odoo/addons/purchase_unreconciled/tests/test_purchase_unreconciled.py
odoo/addons/purchase_unreconciled/views/purchase_order_view.xml
odoo/addons/purchase_unreconciled/views/res_config_settings_view.xml
odoo/addons/purchase_unreconciled/wizards/__init__.py
odoo/addons/purchase_unreconciled/wizards/purchase_unreconciled_exceeded.py
odoo/addons/purchase_unreconciled/wizards/purchase_unreconciled_exceeded_view.xml
odoo_addon_purchase_unreconciled-18.0.1.0.0.4.dist-info/METADATA
odoo_addon_purchase_unreconciled-18.0.1.0.0.4.dist-info/WHEEL
odoo_addon_purchase_unreconciled-18.0.1.0.0.4.dist-info/top_level.txt
odoo_addon_purchase_unreconciled-18.0.1.0.0.4.dist-info/RECORD
