Metadata-Version: 2.1
Name: odoo-addon-purchase_unreconciled
Version: 18.0.1.0.0.4
Requires-Python: >=3.10
Requires-Dist: odoo-addon-account_move_line_purchase_info==18.0.*
Requires-Dist: odoo==18.0.*
Summary: Purchase Unreconciled
Home-page: https://github.com/OCA/account-financial-tools
License: AGPL-3
Author: ForgeFlow S.L., Odoo Community Association (OCA)
Author-email: support@odoo-community.org
Classifier: Programming Language :: Python
Classifier: Framework :: Odoo
Classifier: Framework :: Odoo :: 18.0
Classifier: License :: OSI Approved :: GNU Affero General Public License v3
Classifier: Development Status :: 3 - Alpha
